roar_py_interface/__init__.py
roar_py_interface/actors/__init__.py
roar_py_interface/actors/actor.py
roar_py_interface/actors/vehicle.py
roar_py_interface/base/__init__.py
roar_py_interface/base/sensor.py
roar_py_interface/sensors/__init__.py
roar_py_interface/sensors/accelerometer_sensor.py
roar_py_interface/sensors/camera_sensor.py
roar_py_interface/sensors/collision_sensor.py
roar_py_interface/sensors/custom_lambda_sensor.py
roar_py_interface/sensors/gnss_sensor.py
roar_py_interface/sensors/gyroscope_sensor.py
roar_py_interface/sensors/lidar_sensor.py
roar_py_interface/sensors/location_in_world_sensor.py
roar_py_interface/sensors/occupancy_map_sensor.py
roar_py_interface/sensors/radar_sensor.py
roar_py_interface/sensors/rotation_sensor.py
roar_py_interface/sensors/velocimeter_sensor.py
roar_py_interface/visualizations/__init__.py
roar_py_interface/visualizations/visualizer.py
roar_py_interface/worlds/__init__.py
roar_py_interface/worlds/occupancy_map.py
roar_py_interface/worlds/waypoint.py
roar_py_interface/worlds/world.py
roar_py_interface/wrappers/__init__.py
roar_py_interface/wrappers/actor_sensor_filter.py
roar_py_interface/wrappers/wrapper_base.py
roar_py_remote/__init__.py
roar_py_remote/actors/__init__.py
roar_py_remote/actors/remote_actor_wrappers.py
roar_py_remote/actors/remote_actors.py
roar_py_remote/base/__init__.py
roar_py_remote/base/remote_object.py
roar_py_remote/sensors/__init__.py
roar_py_remote/sensors/remote_sensor_wrappers.py
roar_py_remote/sensors/remote_sensors.py
roar_py_remote/services/__init__.py
roar_py_remote/services/common.py
roar_py_remote/services/websocket_service.py
roar_py_remote/services/base_stream_services/__init__.py
roar_py_remote/services/base_stream_services/base_service.py
roar_py_remote/services/base_stream_services/websocket_service.py
roar_py_remote/worlds/__init__.py
roar_py_remote/worlds/remote_worlds.py
roar_py_remote/worlds/server_worlds.py
roar_py_core-0.1.0.dist-info/LICENSE
roar_py_core-0.1.0.dist-info/METADATA
roar_py_core-0.1.0.dist-info/WHEEL
roar_py_core-0.1.0.dist-info/top_level.txt
roar_py_core-0.1.0.dist-info/RECORD
